Metadata-Version: 2.1
Name: trapi
Version: 1.0
Summary: Time API Wrapper using Python and WorldTimeAPI.org
Home-page: https://nokodaaddictions.github.io
Author: NoKodaAddictions
Author-email: nokodaaddictions@gmail.com
License: UNKNOWN
Platform: UNKNOWN
